fauxgrad/__init__.py
fauxgrad/nn.py
fauxgrad/optim.py
fauxgrad/utils.py
fauxgrad/value.py
fauxgrad-0.2.dist-info/LICENSE
fauxgrad-0.2.dist-info/METADATA
fauxgrad-0.2.dist-info/WHEEL
fauxgrad-0.2.dist-info/top_level.txt
fauxgrad-0.2.dist-info/RECORD
