Metadata-Version: 2.1
Name: fauxgrad
Version: 0.2
Summary: A walkthrough of a small engine for automatic differentiation
Home-page: http://github.com/ksanjeevan/fauxgrad
Author: Kiran Sanjeevan Cabeza
Author-email: ksanjeevancabeza@gmail.com
License: MIT
Keywords: autodiff automatic differentiation python
Platform: UNKNOWN
Classifier: Programming Language :: Python :: 3
Classifier: License :: OSI Approved :: MIT License
Classifier: Operating System :: OS Independent
Requires-Python: >=3.6
License-File: LICENSE
Requires-Dist: micrograd
Requires-Dist: pytest
Requires-Dist: matplotlib
Requires-Dist: numpy
Requires-Dist: networkx
Requires-Dist: sklearn (>=0.21)
Requires-Dist: ipython (>=7.21.0)
